<annotation>
    <folder>train_data</folder>
    <filename>634360_329366.png</filename>
    <size>
        <width>768</width>
        <height>768</height>
        <depth>3</depth>
    </size>
    <object>
        <name>basket_court</name>
        <pose>Unspecified</pose>
        <truncated>0</truncated>
        <occluded>0</occluded>
        <difficult>0</difficult>
        <polygon>
            <x1>387.459332</x1>
            <y1>583.032568</y1>
            <x2>619.673140</x2>
            <y2>586.175709</y2>
            <x3>617.404932</x3>
            <y3>767.794133</y3>
            <x4>385.569771</x4>
            <y4>765.386230</y4>
            <x5>388.863636</x5>
            <y5>586.591119</y5>
        </polygon>
        <bndbox>
            <xmin>385.569763</xmin>
            <ymin>583.032593</ymin>
            <xmax>619.673157</xmax>
            <ymax>767.794128</ymax>
        </bndbox>
    </object>
    <object>
        <name>basket_court</name>
        <pose>Unspecified</pose>
        <truncated>0</truncated>
        <occluded>0</occluded>
        <difficult>0</difficult>
        <polygon>
            <x1>218.990635</x1>
            <y1>360.487136</y1>
            <x2>441.955152</x2>
            <y2>364.994143</y2>
            <x3>442.528638</x3>
            <y3>17.373744</y3>
            <x4>228.493582</x4>
            <y4>11.080109</y4>
            <x5>221.773509</x5>
            <y5>358.505670</y5>
        </polygon>
        <bndbox>
            <xmin>218.990631</xmin>
            <ymin>11.080110</ymin>
            <xmax>442.528625</xmax>
            <ymax>364.994141</ymax>
        </bndbox>
    </object>
</annotation>